yta_stock_downloader/__init__.py
yta_stock_downloader/pexels/__init__.py
yta_stock_downloader/pexels/api.py
yta_stock_downloader/pexels/dataclasses.py
yta_stock_downloader/pexels/enums.py
yta_stock_downloader/pexels/settings.py
yta_stock_downloader/pixabay/__init__.py
yta_stock_downloader/pixabay/api.py
yta_stock_downloader/pixabay/dataclasses.py
yta_stock_downloader/pixabay/enum.py
yta_stock_downloader/pixabay/settings.py
yta_stock_downloader-0.1.9.dist-info/licenses/LICENSE
yta_stock_downloader-0.1.9.dist-info/METADATA
yta_stock_downloader-0.1.9.dist-info/WHEEL
yta_stock_downloader-0.1.9.dist-info/RECORD
